plasmidai/__init__.py
plasmidai/data/__init__.py
plasmidai/data/README.md
plasmidai/data/scripts/1_filter.py
plasmidai/data/scripts/2_partition.py
plasmidai/data/scripts/__init__.py
plasmidai/data/tokenizers/1_tokenizer_bpe.py
plasmidai/data/tokenizers/2_tokenizer_nt.py
plasmidai/data/tokenizers/3_compare_tokenizers.ipynb
plasmidai/data/tokenizers/__init__.py
plasmidai/data/tokenizers/dna_bpe_tokenizer_cutoff_rc.json
plasmidai/data/tokenizers/dna_bpe_tokenizer_offset.json
plasmidai/data/tokenizers/plasmids_replicon_dna_bpe_tokenizer_cutoff_rc.json
plasmidai/data/tokenizers/tokenizer_nt.json
plasmidai/datasets/__init__.py
plasmidai/datasets/plasmid.py
plasmidai/datasets/replicons.py
plasmidai/datasets/utils.py
plasmidai/experimental/__init__.py
plasmidai/experimental/callbacks.py
plasmidai/experimental/lit.py
plasmidai/experimental/optimizers.py
plasmidai/experimental/sample.py
plasmidai/experimental/train.py
plasmidai/paths.py
plasmidai/utils.py
plasmidai-1.2.0.dist-info/LICENSE
plasmidai-1.2.0.dist-info/METADATA
plasmidai-1.2.0.dist-info/WHEEL
plasmidai-1.2.0.dist-info/RECORD
