Metadata-Version: 2.1
Name: plasmidai
Version: 1.2.0
Summary: The largest open-source library to develop plasmid foundation models and generate novel plasmids using machine learning.
Home-page: https://github.com/igem-toronto/plasmidai
License: Apache-2.0
Author: iGEM Toronto
Author-email: Adibvafa.fallahpour@mail.utoronto.ca
Requires-Python: >=3.10,<4.0
Classifier: License :: OSI Approved :: Apache Software License
Classifier: Operating System :: OS Independent
Classifier: Programming Language :: Python :: 3
Classifier: Programming Language :: Python :: 3.10
Classifier: Programming Language :: Python :: 3.11
Classifier: Programming Language :: Python :: 3.12
Requires-Dist: biopython
Requires-Dist: causal-conv1d
Requires-Dist: jsonargparse
Requires-Dist: mamba-ssm
Requires-Dist: numpy
Requires-Dist: packaging
Requires-Dist: pandas
Requires-Dist: pytorch-lightning
Requires-Dist: torch (>=2.2,<3.0)
Requires-Dist: tqdm
Requires-Dist: transformers
Requires-Dist: wandb
Requires-Dist: wheel
Project-URL: Repository, https://github.com/igem-toronto/plasmidai
